resume_processor_pkg/__init__.py
resume_processor_pkg/processor.py
resume_processor_lib_cpp_project-0.0.1.dist-info/LICENSE
resume_processor_lib_cpp_project-0.0.1.dist-info/METADATA
resume_processor_lib_cpp_project-0.0.1.dist-info/WHEEL
resume_processor_lib_cpp_project-0.0.1.dist-info/top_level.txt
resume_processor_lib_cpp_project-0.0.1.dist-info/RECORD
