Metadata-Version: 2.2
Name: resume_processor_lib_cpp_project
Version: 0.0.1
Summary: A library for processing resumes to extract candidate skills
Home-page: 
Author: Your Name
Author-email: your.email@example.com
Classifier: Programming Language :: Python :: 3
Classifier: License :: OSI Approved :: MIT License
Classifier: Operating System :: OS Independent
Requires-Python: >=3.6
License-File: LICENSE
Dynamic: author
Dynamic: author-email
Dynamic: classifier
Dynamic: description-content-type
Dynamic: requires-python
Dynamic: summary
